<?xml version="1.0" encoding="utf-8" ?><dwsync><file name="mplus-2c-hiragana-thin.ttf" server="https://lolipop-7135244fd63eb4a7.webdav-lolipop.jp/art/" local="3496755736" remote="3496755736" Dst="-1" /><file name="mplus-1p-hiragana-bold.ttf" server="https://lolipop-7135244fd63eb4a7.webdav-lolipop.jp/art/" local="3496755736" remote="3496755736" Dst="-1" /><file name="LICENSE_J" server="https://lolipop-7135244fd63eb4a7.webdav-lolipop.jp/art/" local="3496755736" remote="3496755736" Dst="-1" /><file name="mplus-1m-hiragana-regular.ttf" server="https://lolipop-7135244fd63eb4a7.webdav-lolipop.jp/art/" local="3496755736" remote="3496755736" Dst="-1" /><file name="mplus-1c-hiragana-thin.ttf" server="https://lolipop-7135244fd63eb4a7.webdav-lolipop.jp/art/" local="3496755736" remote="3496755736" Dst="-1" /><file name="mplus-2m-hiragana-medium.ttf" server="https://lolipop-7135244fd63eb4a7.webdav-lolipop.jp/art/" local="3496755736" remote="3496755736" Dst="-1" /><file name="mplus-2p-hiragana-regular.ttf" server="https://lolipop-7135244fd63eb4a7.webdav-lolipop.jp/art/" local="3496755736" remote="3496755736" Dst="-1" /><file name="mplus-1c-hiragana-black.ttf" server="https://lolipop-7135244fd63eb4a7.webdav-lolipop.jp/art/" local="3496755736" remote="3496755736" Dst="-1" /><file name="mplus-1p-hiragana-light.ttf" server="https://lolipop-7135244fd63eb4a7.webdav-lolipop.jp/art/" local="3496755736" remote="3496755736" Dst="-1" /><file name="mplus-2c-hiragana-regular.ttf" server="https://lolipop-7135244fd63eb4a7.webdav-lolipop.jp/art/" local="3496755736" remote="3496755736" Dst="-1" /><file name="mplus-1mn-hiragana-light.ttf" server="https://lolipop-7135244fd63eb4a7.webdav-lolipop.jp/art/" local="3496755736" remote="3496755736" Dst="-1" /><file name="mplus-2m-hiragana-regular.ttf" server="https://lolipop-7135244fd63eb4a7.webdav-lolipop.jp/art/" local="3496755736" remote="3496755736" Dst="-1" /><file name="README_E" server="https://lolipop-7135244fd63eb4a7.webdav-lolipop.jp/art/" local="3496755736" remote="3496755736" Dst="-1" /><file name="mplus-2p-hiragana-thin.ttf" server="https://lolipop-7135244fd63eb4a7.webdav-lolipop.jp/art/" local="3496755736" remote="3496755736" Dst="-1" /><file name="mplus-1p-hiragana-medium.ttf" server="https://lolipop-7135244fd63eb4a7.webdav-lolipop.jp/art/" local="3496755736" remote="3496755736" Dst="-1" /><file name="mplus-2c-hiragana-bold.ttf" server="https://lolipop-7135244fd63eb4a7.webdav-lolipop.jp/art/" local="3496755736" remote="3496755736" Dst="-1" /><file name="LICENSE_E" server="https://lolipop-7135244fd63eb4a7.webdav-lolipop.jp/art/" local="3496755736" remote="3496755736" Dst="-1" /><file name="mplus-1m-hiragana-light.ttf" server="https://lolipop-7135244fd63eb4a7.webdav-lolipop.jp/art/" local="3496755736" remote="3496755736" Dst="-1" /><file name="mplus-1c-hiragana-light.ttf" server="https://lolipop-7135244fd63eb4a7.webdav-lolipop.jp/art/" local="3496755736" remote="3496755736" Dst="-1" /><file name="mplus-2p-hiragana-light.ttf" server="https://lolipop-7135244fd63eb4a7.webdav-lolipop.jp/art/" local="3496755736" remote="3496755736" Dst="-1" /><file name="mplus-2c-hiragana-light.ttf" server="https://lolipop-7135244fd63eb4a7.webdav-lolipop.jp/art/" local="3496755736" remote="3496755736" Dst="-1" /><file name="mplus-2p-hiragana-medium.ttf" server="https://lolipop-7135244fd63eb4a7.webdav-lolipop.jp/art/" local="3496755736" remote="3496755736" Dst="-1" /><file name="mplus-1mn-hiragana-bold.ttf" server="https://lolipop-7135244fd63eb4a7.webdav-lolipop.jp/art/" local="3496755736" remote="3496755736" Dst="-1" /><file name="mplus-1c-hiragana-bold.ttf" server="https://lolipop-7135244fd63eb4a7.webdav-lolipop.jp/art/" local="3496755736" remote="3496755736" Dst="-1" /><file name="mplus-1c-hiragana-medium.ttf" server="https://lolipop-7135244fd63eb4a7.webdav-lolipop.jp/art/" local="3496755736" remote="3496755736" Dst="-1" /><file name="mplus-1m-hiragana-bold.ttf" server="https://lolipop-7135244fd63eb4a7.webdav-lolipop.jp/art/" local="3496755736" remote="3496755736" Dst="-1" /><file name="mplus-1m-hiragana-medium.ttf" server="https://lolipop-7135244fd63eb4a7.webdav-lolipop.jp/art/" local="3496755736" remote="3496755736" Dst="-1" /><file name="mplus-1mn-hiragana-medium.ttf" server="https://lolipop-7135244fd63eb4a7.webdav-lolipop.jp/art/" local="3496755736" remote="3496755736" Dst="-1" /><file name="m++ipa.pe" server="https://lolipop-7135244fd63eb4a7.webdav-lolipop.jp/art/" local="3496755736" remote="3496755736" Dst="-1" /><file name="mplus-1mn-hiragana-thin.ttf" server="https://lolipop-7135244fd63eb4a7.webdav-lolipop.jp/art/" local="3496755736" remote="3496755736" Dst="-1" /><file name="mplus-1p-hiragana-regular.ttf" server="https://lolipop-7135244fd63eb4a7.webdav-lolipop.jp/art/" local="3496755736" remote="3496755736" Dst="-1" /><file name="README_J" server="https://lolipop-7135244fd63eb4a7.webdav-lolipop.jp/art/" local="3496755736" remote="3496755736" Dst="-1" /><file name="mplus-1m-hiragana-thin.ttf" server="https://lolipop-7135244fd63eb4a7.webdav-lolipop.jp/art/" local="3496755736" remote="3496755736" Dst="-1" /><file name="mplus-1c-hiragana-heavy.ttf" server="https://lolipop-7135244fd63eb4a7.webdav-lolipop.jp/art/" local="3496755736" remote="3496755736" Dst="-1" /><file name="mplus-2p-hiragana-bold.ttf" server="https://lolipop-7135244fd63eb4a7.webdav-lolipop.jp/art/" local="3496755736" remote="3496755736" Dst="-1" /><file name="mplus-2m-hiragana-bold.ttf" server="https://lolipop-7135244fd63eb4a7.webdav-lolipop.jp/art/" local="3496755736" remote="3496755736" Dst="-1" /></dwsync>