<?xml version="1.0" encoding="utf-8" ?><dwsync><file name=".DS_Store" server="Macintosh HD/Applications/MAMP/htdocs/kaisya/" local="3571614821" remote="3571614821" Dst="-1" /><file name="footer.tpl" server="Macintosh HD/Applications/MAMP/htdocs/kaisya/" local="3569880615" remote="3569880615" Dst="-1" /><file name="head_none.tpl" server="Macintosh HD/Applications/MAMP/htdocs/kaisya/" local="3568849869" remote="3568849869" Dst="-1" /><file name="template.tpl" server="Macintosh HD/Applications/MAMP/htdocs/kaisya/" local="3569805166" remote="3569805166" Dst="-1" /><file name="header_none.tpl" server="Macintosh HD/Applications/MAMP/htdocs/kaisya/" local="3582747397" remote="3582747397" Dst="-1" /><file name=".DS_Store" server="ftp.7135244fd63eb4a7.lolipop.jp" local="3571614821" remote="3571784760" Dst="-1" /><file name="footer.tpl" server="ftp.7135244fd63eb4a7.lolipop.jp" local="3569880615" remote="3571784760" Dst="-1" /><file name="head_none.tpl" server="ftp.7135244fd63eb4a7.lolipop.jp" local="3568849869" remote="3571784760" Dst="-1" /><file name="header_none.tpl" server="ftp.7135244fd63eb4a7.lolipop.jp" local="3582747397" remote="3582747360" Dst="-1" /><file name="template.tpl" server="ftp.7135244fd63eb4a7.lolipop.jp" local="3569805166" remote="3571784760" Dst="-1" /><file name="body_WorksList.tpl" server="Macintosh HD/Applications/MAMP/htdocs/kaisya/" local="3568766490" remote="3568766490" Dst="-1" /><file name="head_WorksList.tpl" server="Macintosh HD/Applications/MAMP/htdocs/kaisya/" local="3568679951" remote="3568679951" Dst="-1" /><file name="head_EditWorks.tpl" server="Macintosh HD/Applications/MAMP/htdocs/kaisya/" local="3568941220" remote="3568941220" Dst="-1" /><file name="body_EditWorks.tpl" server="Macintosh HD/Applications/MAMP/htdocs/kaisya/" local="3568941128" remote="3568941128" Dst="-1" /><file name="body_editworks.tpl" server="ftp.7135244fd63eb4a7.lolipop.jp" local="3582748723" remote="3582748680" Dst="-1" /><file name="body_workslist.tpl" server="ftp.7135244fd63eb4a7.lolipop.jp" local="3571381868" remote="3571784760" Dst="-1" /><file name="head_editworks.tpl" server="ftp.7135244fd63eb4a7.lolipop.jp" local="3579123696" remote="3580157340" Dst="-1" /><file name="head_workslist.tpl" server="ftp.7135244fd63eb4a7.lolipop.jp" local="3568679951" remote="3571784760" Dst="-1" /><file name="body_editworks.tpl" server="Macintosh HD/Applications/MAMP/htdocs/kaisya/" local="3582748723" remote="3582748723" Dst="-1" /><file name="body_workslist.tpl" server="Macintosh HD/Applications/MAMP/htdocs/kaisya/" local="3571381868" remote="3571381868" Dst="-1" /><file name="head_editworks.tpl" server="Macintosh HD/Applications/MAMP/htdocs/kaisya/" local="3579123696" remote="3579123696" Dst="-1" /><file name="head_workslist.tpl" server="Macintosh HD/Applications/MAMP/htdocs/kaisya/" local="3568679951" remote="3568679951" Dst="-1" /><file name="body_regist_artist.tpl" server="Macintosh HD/Applications/MAMP/htdocs/kaisya/" local="3571781434" remote="3571781434" Dst="-1" /><file name="head_regist_artist.tpl" server="Macintosh HD/Applications/MAMP/htdocs/kaisya/" local="3571267755" remote="3571267755" Dst="-1" /><file name="body_regist_artist_done.tpl" server="Macintosh HD/Applications/MAMP/htdocs/kaisya/" local="3569883742" remote="3569883742" Dst="-1" /><file name="body_regist_artist.tpl" server="ftp.7135244fd63eb4a7.lolipop.jp" local="3571781434" remote="3571784760" Dst="-1" /><file name="body_regist_artist_done.tpl" server="ftp.7135244fd63eb4a7.lolipop.jp" local="3569883742" remote="3571784760" Dst="-1" /><file name="head_regist_artist.tpl" server="ftp.7135244fd63eb4a7.lolipop.jp" local="3571267755" remote="3571784760" Dst="-1" /><file name="header_menu.tpl" server="Macintosh HD/Applications/MAMP/htdocs/kaisya/" local="3581973185" remote="3581973185" Dst="-1" /><file name="header_menu.tpl" server="ftp.7135244fd63eb4a7.lolipop.jp" local="3581973185" remote="3582007140" Dst="-1" /><file name="body_artist_login.tpl" server="Macintosh HD/Applications/MAMP/htdocs/kaisya/" local="3571359412" remote="3571359412" Dst="-1" /><file name="body_artist_lostpassword.tpl" server="Macintosh HD/Applications/MAMP/htdocs/kaisya/" local="3571617489" remote="3571617489" Dst="-1" /><file name="body_session_out.tpl" server="Macintosh HD/Applications/MAMP/htdocs/kaisya/" local="3571382643" remote="3571382643" Dst="-1" /><file name="body_artist_logout.tpl" server="Macintosh HD/Applications/MAMP/htdocs/kaisya/" local="3571384278" remote="3571384278" Dst="-1" /><file name="body_artist_login.tpl" server="ftp.7135244fd63eb4a7.lolipop.jp" local="3571359412" remote="3571784760" Dst="-1" /><file name="body_artist_logout.tpl" server="ftp.7135244fd63eb4a7.lolipop.jp" local="3571384278" remote="3571784760" Dst="-1" /><file name="body_artist_lostpassword.tpl" server="ftp.7135244fd63eb4a7.lolipop.jp" local="3571617489" remote="3571784760" Dst="-1" /><file name="body_session_out.tpl" server="ftp.7135244fd63eb4a7.lolipop.jp" local="3571382643" remote="3571784760" Dst="-1" /><file name="body_artist_changepassword.tpl" server="ftp.7135244fd63eb4a7.lolipop.jp" local="3571617548" remote="3571784760" Dst="-1" /><file name="body_artist_changepassword.tpl" server="Macintosh HD/Applications/MAMP/htdocs/kaisya/" local="3571617548" remote="3571617548" Dst="-1" /><file name="body_order_list.tpl" server="Macintosh HD/Applications/MAMP/htdocs/kaisya/" local="3581923389" remote="3581923389" Dst="-1" /><file name="body_order_detail.tpl" server="Macintosh HD/Applications/MAMP/htdocs/kaisya/" local="3582700555" remote="3582700555" Dst="-1" /><file name="body_order_cancel.tpl" server="Macintosh HD/Applications/MAMP/htdocs/kaisya/" local="3581921035" remote="3581921035" Dst="-1" /><file name="body_order_cancel.tpl" server="ftp.7135244fd63eb4a7.lolipop.jp" local="3581921035" remote="3582007140" Dst="-1" /><file name="body_order_detail.tpl" server="ftp.7135244fd63eb4a7.lolipop.jp" local="3582700555" remote="3582701760" Dst="-1" /><file name="body_order_list.tpl" server="ftp.7135244fd63eb4a7.lolipop.jp" local="3581923389" remote="3582007140" Dst="-1" /><file name="head_order_detail.tpl" server="Macintosh HD/Applications/MAMP/htdocs/kaisya/" local="3582700428" remote="3582700428" Dst="-1" /><file name="head_order_detail.tpl" server="ftp.7135244fd63eb4a7.lolipop.jp" local="3582700428" remote="3582701760" Dst="-1" /><file name=".DS_Store" server="Macintosh HD/Applications/MAMP/htdocs/art/" local="3583466929" remote="3583466929" Dst="-1" /><file name="body_artist_changepassword.tpl" server="Macintosh HD/Applications/MAMP/htdocs/art/" local="3583466929" remote="3583466929" Dst="-1" /><file name="body_artist_login.tpl" server="Macintosh HD/Applications/MAMP/htdocs/art/" local="3583466929" remote="3583466929" Dst="-1" /><file name="body_artist_logout.tpl" server="Macintosh HD/Applications/MAMP/htdocs/art/" local="3583466929" remote="3583466929" Dst="-1" /><file name="body_artist_lostpassword.tpl" server="Macintosh HD/Applications/MAMP/htdocs/art/" local="3583466929" remote="3583466929" Dst="-1" /><file name="body_editworks.tpl" server="Macintosh HD/Applications/MAMP/htdocs/art/" local="3583466929" remote="3583466929" Dst="-1" /><file name="body_order_cancel.tpl" server="Macintosh HD/Applications/MAMP/htdocs/art/" local="3583466929" remote="3583466929" Dst="-1" /><file name="body_order_detail.tpl" server="Macintosh HD/Applications/MAMP/htdocs/art/" local="3583466929" remote="3583466929" Dst="-1" /><file name="body_order_list.tpl" server="Macintosh HD/Applications/MAMP/htdocs/art/" local="3583466929" remote="3583466929" Dst="-1" /><file name="body_regist_artist.tpl" server="Macintosh HD/Applications/MAMP/htdocs/art/" local="3583466929" remote="3583466929" Dst="-1" /><file name="body_regist_artist_done.tpl" server="Macintosh HD/Applications/MAMP/htdocs/art/" local="3583466929" remote="3583466929" Dst="-1" /><file name="body_session_out.tpl" server="Macintosh HD/Applications/MAMP/htdocs/art/" local="3583466929" remote="3583466929" Dst="-1" /><file name="body_workslist.tpl" server="Macintosh HD/Applications/MAMP/htdocs/art/" local="3583466929" remote="3583466929" Dst="-1" /><file name="footer.tpl" server="Macintosh HD/Applications/MAMP/htdocs/art/" local="3584002478" remote="3584002478" Dst="-1" /><file name="head_editworks.tpl" server="Macintosh HD/Applications/MAMP/htdocs/art/" local="3583466929" remote="3583466929" Dst="-1" /><file name="head_none.tpl" server="Macintosh HD/Applications/MAMP/htdocs/art/" local="3583466929" remote="3583466929" Dst="-1" /><file name="head_order_detail.tpl" server="Macintosh HD/Applications/MAMP/htdocs/art/" local="3583466929" remote="3583466929" Dst="-1" /><file name="head_regist_artist.tpl" server="Macintosh HD/Applications/MAMP/htdocs/art/" local="3583466929" remote="3583466929" Dst="-1" /><file name="head_workslist.tpl" server="Macintosh HD/Applications/MAMP/htdocs/art/" local="3583466929" remote="3583466929" Dst="-1" /><file name="header_menu.tpl" server="Macintosh HD/Applications/MAMP/htdocs/art/" local="3584003208" remote="3584003208" Dst="-1" /><file name="header_none.tpl" server="Macintosh HD/Applications/MAMP/htdocs/art/" local="3583466929" remote="3583466929" Dst="-1" /><file name="template.tpl" server="Macintosh HD/Applications/MAMP/htdocs/art/" local="3583995145" remote="3583995145" Dst="-1" /><file name="body_teikei.tpl" server="Macintosh HD/Applications/MAMP/htdocs/art/" local="3584002813" remote="3584002813" Dst="-1" /></dwsync>