<?xml version="1.0" encoding="utf-8" ?><dwsync><file name="style.css" server="Macintosh HD/Applications/MAMP/htdocs/kaisya/" local="3581973105" remote="3581973105" Dst="-1" /><file name="style.css" server="ftp.7135244fd63eb4a7.lolipop.jp" local="3581973105" remote="3582007080" Dst="-1" /><file name="style_WorksList.css" server="Macintosh HD/Applications/MAMP/htdocs/kaisya/" local="3568766224" remote="3568766224" Dst="-1" /><file name="style_EditWorks.css" server="Macintosh HD/Applications/MAMP/htdocs/kaisya/" local="3568849785" remote="3568849785" Dst="-1" /><file name="style_editworks.css" server="ftp.7135244fd63eb4a7.lolipop.jp" local="3570781851" remote="3571784760" Dst="-1" /><file name="style_workslist.css" server="ftp.7135244fd63eb4a7.lolipop.jp" local="3580366727" remote="3582007080" Dst="-1" /><file name="style_editworks.css" server="Macintosh HD/Applications/MAMP/htdocs/kaisya/" local="3570781851" remote="3570781851" Dst="-1" /><file name="style_workslist.css" server="Macintosh HD/Applications/MAMP/htdocs/kaisya/" local="3580366727" remote="3580366727" Dst="-1" /></dwsync>